<?xml version="1.0" encoding="utf-8"?>
<CAVE>
  <Sensor>
    <Pos.X>0.05</Pos.X>
    <Pos.Y>2.125789</Pos.Y>
    <Pos.Z>1.5</Pos.Z>
    <Rot.X>25.30008</Rot.X>
    <Rot.Y>181.4123</Rot.Y>
    <Rot.Z>0.436350733</Rot.Z>
  </Sensor>
  <Projectors>
    <Projector>
      <Pos.X>0.081</Pos.X>
      <Pos.Y>2.4</Pos.Y>
      <Pos.Z>-0.4</Pos.Z>
      <Rot.Y>-0.842</Rot.Y>
      <Rot.X>1.5444</Rot.X>
      <Rot.Z>0</Rot.Z>
      <Fy>-1.25</Fy>
      <FOV>58.89</FOV>
      <Display>1</Display>
    </Projector>
    <Projector>
      <Pos.X>0.482</Pos.X>
      <Pos.Y>2.333</Pos.Y>
      <Pos.Z>0.0956</Pos.Z>
      <Rot.Y>269</Rot.Y>
      <Rot.X>0.116</Rot.X>
      <Rot.Z>0</Rot.Z>
      <Fy>-1.259</Fy>
      <FOV>58.68</FOV>
      <Display>2</Display>
    </Projector>
    <Projector>
      <Pos.X>-0.5</Pos.X>
      <Pos.Y>2.328</Pos.Y>
      <Pos.Z>-0.161</Pos.Z>
      <Rot.Y>88.112</Rot.Y>
      <Rot.X>0</Rot.X>
      <Rot.Z>0</Rot.Z>
      <Fy>-1.2492</Fy>
      <FOV>58.06</FOV>
      <Display>3</Display>
    </Projector>
    <Projector>
      <Pos.X>-0.1031942</Pos.X>
      <Pos.Y>2.358713</Pos.Y>
      <Pos.Z>0.8253639</Pos.Z>
      <Rot.Y>0</Rot.Y>
      <Rot.X>67.14233</Rot.X>
      <Rot.Z>0</Rot.Z>
      <Fy>-1.2</Fy>
      <FOV>61.911</FOV>
      <Display>4</Display>
    </Projector>
  </Projectors>
  <Surfaces>
    <Surface>
      <!-- Front Wall -->
      <Pos.X>0</Pos.X>
      <Pos.Y>1</Pos.Y>
      <Pos.Z>1.4</Pos.Z>
      <Rot.X>-90</Rot.X>
      <Rot.Y>0</Rot.Y>
      <Rot.Z>0</Rot.Z>
      <Size.X>2.8</Size.X> <!-- Width -->
      <Size.Y>0.01</Size.Y>
      <Size.Z>2</Size.Z><!-- Height -->
      <Vertices>
        <BottomLeft.X>.12063</BottomLeft.X>
        <BottomLeft.Y>.02556</BottomLeft.Y>
        <TopLeft.X>.10625</TopLeft.X>
        <TopLeft.Y>.97444</TopLeft.Y>
        <TopRight.X>.86813</TopRight.X>
        <TopRight.Y>.96778</TopRight.Y>
        <BottomRight.X>.87313</BottomRight.X>
        <BottomRight.Y>.00778</BottomRight.Y>
      </Vertices>
      <Display>1</Display>
    </Surface>
    <Surface>
      <!-- Left Wall -->
      <Pos.X>-1.4</Pos.X>
      <Pos.Y>1</Pos.Y>
      <Pos.Z>0</Pos.Z>
      <Rot.X>-90</Rot.X>
      <Rot.Y>-90</Rot.Y>
      <Rot.Z>0</Rot.Z>
      <Size.X>2.8</Size.X><!-- Width -->
      <Size.Y>0.01</Size.Y>
      <Size.Z>2</Size.Z><!-- Height -->
      <Vertices>
        <BottomLeft.X>.11979</BottomLeft.X>
        <BottomLeft.Y>.04815</BottomLeft.Y>
        <TopLeft.X>.12565</TopLeft.X>
        <TopLeft.Y>.99074</TopLeft.Y>
        <TopRight.X>.85833</TopRight.X>
        <TopRight.Y>.97963</TopRight.Y>
        <BottomRight.X>.85990</BottomRight.X>
        <BottomRight.Y>.03148</BottomRight.Y>
      </Vertices>
      <Display>2</Display>
    </Surface>
    <Surface>
      <!-- Right Wall -->
      <Pos.X>1.4</Pos.X>
      <Pos.Y>1</Pos.Y>
      <Pos.Z>0</Pos.Z>
      <Rot.X>-90</Rot.X>
      <Rot.Y>90</Rot.Y>
      <Rot.Z>0</Rot.Z>
      <Size.X>2.8</Size.X><!-- Width -->
      <Size.Y>0.01</Size.Y>
      <Size.Z>2</Size.Z><!-- Height -->
      <Vertices>
        <BottomLeft.X>.11354</BottomLeft.X>
        <BottomLeft.Y>.06111</BottomLeft.Y>
        <TopLeft.X>.11875</TopLeft.X>
        <TopLeft.Y>.98889</TopLeft.Y>
        <TopRight.X>.85677</TopRight.X>
        <TopRight.Y>.95278</TopRight.Y>
        <BottomRight.X>.85104</BottomRight.X>
        <BottomRight.Y>.00648</BottomRight.Y>
      </Vertices>
      <Display>3</Display>
    </Surface>
    <Surface>
      <!-- Floor -->
      <Pos.X>0</Pos.X>
      <Pos.Y>0</Pos.Y>
      <Pos.Z>0.5</Pos.Z>
      <Rot.X>0</Rot.X>
      <Rot.Y>0</Rot.Y>
      <Rot.Z>0</Rot.Z>
      <Size.X>2.8</Size.X>
      <Size.Y>0.01</Size.Y>
      <Size.Z>1.8</Size.Z>
      <Vertices>
        <BottomLeft.X>.10234</BottomLeft.X>
        <BottomLeft.Y>.09375</BottomLeft.Y>
        <TopLeft.X>.21953</TopLeft.X>
        <TopLeft.Y>.96500</TopLeft.Y>
        <TopRight.X>.83203</TopRight.X>
        <TopRight.Y>.96125</TopRight.Y>
        <BottomRight.X>.97109</BottomRight.X>
        <BottomRight.Y>.04750</BottomRight.Y>
      </Vertices>
      <Display>4</Display>
    </Surface>-->
  </Surfaces>
</CAVE>